LICENSE.txt
README.rst
setup.cfg
setup.py
pysura/__init__.py
pysura.egg-info/PKG-INFO
pysura.egg-info/SOURCES.txt
pysura.egg-info/dependency_links.txt
pysura.egg-info/entry_points.txt
pysura.egg-info/requires.txt
pysura.egg-info/top_level.txt
pysura/cli/__init__.py
pysura/cli/app.py
pysura/cli/google_root.py
pysura/faster_api/__init__.py
pysura/faster_api/enums.py
pysura/faster_api/models.py
pysura/faster_api/security.py
pysura/library_data/pysura_auth/.gcloudignore
pysura/library_data/pysura_auth/main.py
pysura/library_data/pysura_auth/requirements.txt
pysura/library_data/pysura_frontend/build.yaml
pysura/library_data/pysura_frontend/pubspec.yaml
pysura/library_data/pysura_frontend/lib/main.dart
pysura/library_data/pysura_frontend/lib/common/app_color.dart
pysura/library_data/pysura_frontend/lib/common/app_route.dart
pysura/library_data/pysura_frontend/lib/common/app_text_style.dart
pysura/library_data/pysura_frontend/lib/common/app_theme.dart
pysura/library_data/pysura_frontend/lib/common/constants.dart
pysura/library_data/pysura_frontend/lib/common/date_util.dart
pysura/library_data/pysura_frontend/lib/common/popups.dart
pysura/library_data/pysura_frontend/lib/common/utils.dart
pysura/library_data/pysura_frontend/lib/controllers/auth_controller.dart
pysura/library_data/pysura_frontend/lib/controllers/data_controller.dart
pysura/library_data/pysura_frontend/lib/controllers/graphql_controller.dart
pysura/library_data/pysura_frontend/lib/controllers/theme_controller.dart
pysura/library_data/pysura_frontend/lib/graphql/actions.graphql
pysura/library_data/pysura_frontend/lib/graphql/actions.graphql.dart
pysura/library_data/pysura_frontend/lib/graphql/schema.graphql
pysura/library_data/pysura_frontend/lib/graphql/schema.graphql.dart
pysura/library_data/pysura_frontend/lib/graphql/user.graphql
pysura/library_data/pysura_frontend/lib/graphql/user.graphql.dart
pysura/library_data/pysura_frontend/lib/pages/auth/login_page.dart
pysura/library_data/pysura_frontend/lib/pages/auth/login_page_controller.dart
pysura/library_data/pysura_frontend/lib/pages/main/main_page.dart
pysura/library_data/pysura_frontend/lib/pages/main/main_page_controller.dart
