Metadata-Version: 2.1
Name: pysura
Version: 0.99.139
Summary: A useful tool that provides commands to help ease the installation process of Hasura, and manage its actions, events, and scheduled jobs with baked in phone Auth and a Flutter frontend.
Home-page: https://github.com/tristengoodz/pysura
Author: Tristen Harr
Author-email: tristen@thegoodzapp.com
Keywords: hasura,graphql,postgresql,google-cloud,python,pysura,backend,backend-in-a-box
Classifier: Development Status :: 4 - Beta
Classifier: Intended Audience :: Developers
Classifier: Topic :: Software Development :: Build Tools
Classifier: License :: OSI Approved :: MIT License
Classifier: Programming Language :: Python :: 3
Requires-Python: >=3.9
License-File: LICENSE.txt
